isoc_ams.py
isoc_ams-0.1.2.dist-info/licenses/LICENSE
isoc_ams-0.1.2.dist-info/WHEEL
isoc_ams-0.1.2.dist-info/METADATA
isoc_ams-0.1.2.dist-info/RECORD
