Metadata-Version: 2.4
Name: isoc-ams
Version: 0.1.2
Summary: A Python 3 module to cope with ISOC-AMS.
Author-email: Klaus Birkenbihl <klaus.birkenbihl@isoc.de>
Maintainer: Klaus Birkenbihl
Classifier: License :: OSI Approved :: MIT License
License-File: LICENSE
Requires-Dist: selenium>4
Project-URL: Home, https://github.com/birkenbihl/isoc-ams
